<?xml version="1.0" encoding="UTF-8" standalone="yes"?><imgdir name="01072869.img"><imgdir name="info"><canvas name="icon" width="29" height="31"><vector name="origin" x="-1" y="30"/><string name="_hash" value="5d0a8f69d401880ed3bf2b781ed955bba7a0a19cd0e8abcfcacbda289360e4af"/></canvas><canvas name="iconRaw" width="29" height="30"><vector name="origin" x="-1" y="30"/><string name="_hash" value="9d6d168a9417319bb736bf3282d6a2dea4c36e9f23f46a8267f959ba42be50cb"/></canvas><string name="islot" value="So"/><string name="vslot" value="So"/><int name="reqJob" value="0"/><int name="reqLevel" value="0"/><int name="reqSTR" value="0"/><int name="reqDEX" value="0"/><int name="reqINT" value="0"/><int name="reqLUK" value="0"/><int name="cash" value="1"/></imgdir><imgdir name="walk1"><imgdir name="0"><canvas name="shoes" width="16" height="13"><vector name="origin" x="2" y="-8"/><imgdir name="map"><vector name="navel" x="0" y="0"/></imgdir><string name="z" value="shoes"/><string name="_hash" value="dc51acad372c5f90cf501207551bcfbd5086bfb0ef5928ba43d74280dc068a7b"/></canvas></imgdir><imgdir name="1"><canvas name="shoes" width="26" height="13"><vector name="origin" x="10" y="-8"/><imgdir name="map"><vector name="navel" x="0" y="0"/></imgdir><string name="z" value="shoes"/><string name="_hash" value="5ae9339651c72c4b9b7be84b5a60231d19e586183a00c7d39936219ba563bfda"/></canvas></imgdir><imgdir name="2"><canvas name="shoes" width="14" height="13"><vector name="origin" x="2" y="-8"/><imgdir name="map"><vector name="navel" x="0" y="0"/></imgdir><string name="z" value="shoes"/><string name="_hash" value="7268e15d970831ccf7679ed0b87bba74d0f57580130b6eada4303df95ead1abc"/></canvas></imgdir><imgdir name="3"><canvas name="shoes" width="24" height="13"><vector name="origin" x="9" y="-6"/><imgdir name="map"><vector name="navel" x="0" y="0"/></imgdir><string name="z" value="shoes"/><string name="_hash" value="d7d5dcda475e099b56af75f6650b0d6ea04309af9e1aa83508c1cec412bcc7ac"/></canvas></imgdir></imgdir><imgdir name="walk2"><imgdir name="0"><uol name="shoes" value="../../walk1/0/shoes"/></imgdir><imgdir name="1"><uol name="shoes" value="../../walk1/1/shoes"/></imgdir><imgdir name="2"><uol name="shoes" value="../../walk1/2/shoes"/></imgdir><imgdir name="3"><uol name="shoes" value="../../walk1/3/shoes"/></imgdir></imgdir><imgdir name="stand1"><imgdir name="0"><canvas name="shoes" width="21" height="13"><vector name="origin" x="7" y="-9"/><imgdir name="map"><vector name="navel" x="0" y="0"/></imgdir><string name="z" value="shoes"/><string name="_hash" value="e7380ebaa396f5391a008f9706368cd2cf31d32c895a197d7ffd68177faf912e"/></canvas></imgdir><imgdir name="1"><canvas name="shoes" width="21" height="13"><vector name="origin" x="8" y="-8"/><imgdir name="map"><vector name="navel" x="0" y="0"/></imgdir><string name="z" value="shoes"/><string name="_hash" value="995c237226196922ff28eea75c2b3d7549272f4b7ddd87101bf2df83d500cbf6"/></canvas></imgdir><imgdir name="2"><canvas name="shoes" width="21" height="13"><vector name="origin" x="9" y="-9"/><imgdir name="map"><vector name="navel" x="0" y="0"/></imgdir><string name="z" value="shoes"/><string name="_hash" value="42e551dfdbef02c41d12913bc72be56ed0576c3277509ffc24f0ecf60f3d6f26"/></canvas></imgdir></imgdir><imgdir name="stand2"><imgdir name="0"><uol name="shoes" value="../../stand1/0/shoes"/></imgdir><imgdir name="1"><uol name="shoes" value="../../stand1/1/shoes"/></imgdir><imgdir name="2"><uol name="shoes" value="../../stand1/2/shoes"/></imgdir></imgdir><imgdir name="alert"><imgdir name="0"><canvas name="shoes" width="25" height="11"><vector name="origin" x="13" y="-8"/><imgdir name="map"><vector name="navel" x="0" y="0"/></imgdir><string name="z" value="shoes"/><string name="_hash" value="d5d65d91f2d8ba8e8f4628fbdcd51239b6c93b4cc66807e100b4b8ed42867b04"/></canvas></imgdir><imgdir name="1"><canvas name="shoes" width="25" height="11"><vector name="origin" x="13" y="-9"/><imgdir name="map"><vector name="navel" x="0" y="0"/></imgdir><string name="z" value="shoes"/><string name="_hash" value="bff69a0b8439e620ce337aa2d9c7341a8bce8b3ef4640f3fbf2ce8377260d41f"/></canvas></imgdir><imgdir name="2"><canvas name="shoes" width="25" height="12"><vector name="origin" x="13" y="-9"/><imgdir name="map"><vector name="navel" x="0" y="0"/></imgdir><string name="z" value="shoes"/><string name="_hash" value="7602f64535b12c2abf540d4edbcbf6845fbf372425465d6377c853fe07839935"/></canvas></imgdir></imgdir><imgdir name="swingO1"><imgdir name="0"><canvas name="shoes" width="28" height="12"><vector name="origin" x="10" y="-5"/><imgdir name="map"><vector name="navel" x="0" y="0"/></imgdir><string name="z" value="shoes"/><string name="_hash" value="8cf63c151a33de6b28e444fa821c143a0373e9d2ea223fea97fa7dd26b9cbd28"/></canvas></imgdir><imgdir name="1"><canvas name="shoes" width="16" height="12"><vector name="origin" x="3" y="-9"/><imgdir name="map"><vector name="navel" x="0" y="0"/></imgdir><string name="z" value="shoes"/><string name="_hash" value="e419d0c1b15d9f72f77fc5ce145705a0805940d466c73d0cfd1867c29d661fdf"/></canvas></imgdir><imgdir name="2"><canvas name="shoes" width="37" height="13"><vector name="origin" x="8" y="-5"/><imgdir name="map"><vector name="navel" x="0" y="0"/></imgdir><string name="z" value="shoes"/><string name="_hash" value="1dce9cd6a2173e9d49af78152d70b1561177a93f9e4ac74f1d40366696db48c8"/></canvas></imgdir></imgdir><imgdir name="swingO2"><imgdir name="0"><canvas name="shoes" width="23" height="13"><vector name="origin" x="11" y="-8"/><imgdir name="map"><vector name="navel" x="0" y="0"/></imgdir><string name="z" value="shoes"/><string name="_hash" value="0bb26754b047f05f701749459e1924f8e779f57e58c4a15a19887432d677b91b"/></canvas></imgdir><imgdir name="1"><canvas name="shoes" width="28" height="12"><vector name="origin" x="13" y="-7"/><imgdir name="map"><vector name="navel" x="0" y="0"/></imgdir><string name="z" value="shoes"/><string name="_hash" value="1f66e2e51ab2f92e3d6dc873731b078ee41d3442747b41b71356851c32a664d4"/></canvas></imgdir><imgdir name="2"><canvas name="shoes" width="29" height="12"><vector name="origin" x="12" y="-5"/><imgdir name="map"><vector name="navel" x="0" y="0"/></imgdir><string name="z" value="shoes"/><string name="_hash" value="fd9b61d7f7d2ce9aefaf4a5c58c3d243981143e69621bf51c1f670bc106d0027"/></canvas></imgdir></imgdir><imgdir name="swingO3"><imgdir name="0"><canvas name="shoes" width="27" height="11"><vector name="origin" x="8" y="-6"/><imgdir name="map"><vector name="navel" x="0" y="0"/></imgdir><string name="z" value="shoes"/><string name="_hash" value="61dda7cc464aad0cd9bd347a7c06d60e0d470e744463aa3e59416ca1f4e4ef95"/></canvas></imgdir><imgdir name="1"><canvas name="shoes" width="19" height="12"><vector name="origin" x="2" y="-6"/><imgdir name="map"><vector name="navel" x="0" y="0"/></imgdir><string name="z" value="shoes"/><string name="_hash" value="6ed4b14151d8531c705c57510b7407fcee9118d55c653cf9a40571cb07461524"/></canvas></imgdir><imgdir name="2"><canvas name="shoes" width="28" height="12"><vector name="origin" x="6" y="-5"/><imgdir name="map"><vector name="navel" x="0" y="0"/></imgdir><string name="z" value="shoes"/><string name="_inlink" value="swingO1/0/shoes"/></canvas></imgdir></imgdir><imgdir name="swingOF"><imgdir name="0"><canvas name="shoes" width="30" height="11"><vector name="origin" x="15" y="-7"/><imgdir name="map"><vector name="navel" x="0" y="0"/></imgdir><string name="z" value="shoes"/><string name="_hash" value="b4c3c0267cba8a2f86d9f9cf0a6dc6bebac4148450c10422c47209203c982c8f"/></canvas></imgdir><imgdir name="1"><canvas name="shoes" width="25" height="18"><vector name="origin" x="9" y="-7"/><imgdir name="map"><vector name="navel" x="0" y="0"/></imgdir><string name="z" value="backShoes"/><string name="_hash" value="267eb4f2ea1faeb0c85ee33c7a84e748d4b015f3724ffe32fc6117b1e52752dd"/></canvas></imgdir><imgdir name="2"><canvas name="shoes" width="15" height="19"><vector name="origin" x="3" y="-2"/><imgdir name="map"><vector name="navel" x="0" y="0"/></imgdir><string name="z" value="shoes"/><string name="_hash" value="78d47f4af6f58c59aceb40f40d60917536302a9ef320261078a6bee084fb3236"/></canvas></imgdir><imgdir name="3"><canvas name="shoes" width="36" height="13"><vector name="origin" x="16" y="0"/><imgdir name="map"><vector name="navel" x="0" y="0"/></imgdir><string name="z" value="shoes"/><string name="_hash" value="fc134154a929f6330dd23678b58d1288bf717e604c77b14644e8407605bab09f"/></canvas></imgdir></imgdir><imgdir name="swingT1"><imgdir name="0"><canvas name="shoes" width="23" height="13"><vector name="origin" x="11" y="-9"/><imgdir name="map"><vector name="navel" x="0" y="0"/></imgdir><string name="z" value="shoes"/><string name="_hash" value="bd447e257a3ce8ae18f3e5b9a15d666a7d967f04b5fdfba385991ab6fdc5b572"/></canvas></imgdir><imgdir name="1"><canvas name="shoes" width="28" height="12"><vector name="origin" x="12" y="-7"/><imgdir name="map"><vector name="navel" x="0" y="0"/></imgdir><string name="z" value="shoes"/><string name="_hash" value="ec99bd7fead61f8a384c8cb3db9290a6a1469ab68a08eb9d177a6336ef278705"/></canvas></imgdir><imgdir name="2"><canvas name="shoes" width="37" height="13"><vector name="origin" x="10" y="-5"/><imgdir name="map"><vector name="navel" x="0" y="0"/></imgdir><string name="z" value="shoes"/><string name="_hash" value="781eed4d0621468dc22ce95c64f44639092311b2e337e5009c22be2c9f8b3bd5"/></canvas></imgdir></imgdir><imgdir name="swingT2"><imgdir name="0"><canvas name="shoes" width="28" height="17"><vector name="origin" x="15" y="-2"/><imgdir name="map"><vector name="navel" x="0" y="0"/></imgdir><string name="z" value="shoes"/><string name="_hash" value="8f1b3e2404fba2d5a0562163dc34590c21678ccb974fb72e119adc01083c8838"/></canvas></imgdir><imgdir name="1"><canvas name="shoes" width="28" height="13"><vector name="origin" x="11" y="-6"/><imgdir name="map"><vector name="navel" x="0" y="0"/></imgdir><string name="z" value="shoes"/><string name="_hash" value="040ebfd177eb93b4960d798ed55b838d703d02f5285f9a526d37c324bed49ee2"/></canvas></imgdir><imgdir name="2"><canvas name="shoes" width="37" height="13"><vector name="origin" x="11" y="-4"/><imgdir name="map"><vector name="navel" x="0" y="0"/></imgdir><string name="z" value="shoes"/><string name="_hash" value="34cbd413f0ab3aa9faefd1f1d54e7ae40e628af8762220564ca73a9c39e0476a"/></canvas></imgdir></imgdir><imgdir name="swingT3"><imgdir name="0"><canvas name="shoes" width="29" height="12"><vector name="origin" x="13" y="-7"/><imgdir name="map"><vector name="navel" x="0" y="0"/></imgdir><string name="z" value="shoes"/><string name="_hash" value="20b0ff117d232392fb29601719cc95df93aa8cbef07c51621891a2fe4d5a6613"/></canvas></imgdir><imgdir name="1"><canvas name="shoes" width="26" height="11"><vector name="origin" x="6" y="-6"/><imgdir name="map"><vector name="navel" x="0" y="0"/></imgdir><string name="z" value="shoes"/><string name="_hash" value="9d21e4873416288a3aaa1a399f8aca8c7dedc7a0d5a315c5974dcbbc07a7ccc6"/></canvas></imgdir><imgdir name="2"><canvas name="shoes" width="37" height="13"><vector name="origin" x="11" y="-5"/><imgdir name="map"><vector name="navel" x="0" y="0"/></imgdir><string name="z" value="shoes"/><string name="_inlink" value="swingT2/2/shoes"/></canvas></imgdir></imgdir><imgdir name="swingTF"><imgdir name="0"><canvas name="shoes" width="11" height="15"><vector name="origin" x="3" y="-7"/><imgdir name="map"><vector name="navel" x="0" y="0"/></imgdir><string name="z" value="backShoes"/><string name="_hash" value="0b1c447b604fe579aa0ed79c62aefd97dcca83f11c0b14820bc4b61f46857641"/></canvas></imgdir><imgdir name="1"><canvas name="shoes" width="19" height="17"><vector name="origin" x="7" y="-6"/><imgdir name="map"><vector name="navel" x="0" y="0"/></imgdir><string name="z" value="shoes"/><string name="_hash" value="2640012096280e2385db1d047d21676aa7edde51de9ef523b3840ee5563486cf"/></canvas></imgdir><imgdir name="2"><canvas name="shoes" width="27" height="13"><vector name="origin" x="8" y="-6"/><imgdir name="map"><vector name="navel" x="0" y="0"/></imgdir><string name="z" value="shoes"/><string name="_hash" value="de9bfea8df259321d583a37af1258065edadca87f0fd287998bb654d622de48a"/></canvas></imgdir><imgdir name="3"><canvas name="shoes" width="37" height="13"><vector name="origin" x="12" y="-3"/><imgdir name="map"><vector name="navel" x="0" y="0"/></imgdir><string name="z" value="shoes"/><string name="_inlink" value="swingT2/2/shoes"/></canvas></imgdir></imgdir><imgdir name="ladder"><imgdir name="0"><canvas name="shoes" width="17" height="15"><vector name="origin" x="9" y="-7"/><imgdir name="map"><vector name="navel" x="0" y="0"/></imgdir><string name="z" value="backShoes"/><string name="_hash" value="9f471858f01535d56aa6477d857b0b33dbde3d61ba5abf5792ef2aec6dc799d2"/></canvas></imgdir><imgdir name="1"><canvas name="shoes" width="17" height="15"><vector name="origin" x="8" y="-7"/><imgdir name="map"><vector name="navel" x="0" y="0"/></imgdir><string name="z" value="backShoes"/><string name="_hash" value="fae24fcc2b8145de8301acd15ca11c54ebd0b09c3185d7f725e6628650962fe1"/></canvas></imgdir></imgdir><imgdir name="stabO1"><imgdir name="0"><canvas name="shoes" width="34" height="13"><vector name="origin" x="20" y="-5"/><imgdir name="map"><vector name="navel" x="0" y="0"/></imgdir><string name="z" value="shoes"/><string name="_hash" value="b3007669d5fd8de5b93a72c7b72adfbe656fdc619ce3b7cc5bca8fd1f910ea12"/></canvas></imgdir><imgdir name="1"><canvas name="shoes" width="34" height="13"><vector name="origin" x="11" y="-3"/><imgdir name="map"><vector name="navel" x="0" y="0"/></imgdir><string name="z" value="shoes"/><string name="_hash" value="2343e1ab32038d37e572983332646a5af141b2a194e0317d7605ea027bbabd1f"/></canvas></imgdir></imgdir><imgdir name="stabO2"><imgdir name="0"><canvas name="shoes" width="26" height="14"><vector name="origin" x="13" y="-7"/><imgdir name="map"><vector name="navel" x="0" y="0"/></imgdir><string name="z" value="shoes"/><string name="_hash" value="af9ce10906747b6ae954a6df45d073c1528df581c6e5788222ed083554d62ce0"/></canvas></imgdir><imgdir name="1"><canvas name="shoes" width="37" height="13"><vector name="origin" x="10" y="-4"/><imgdir name="map"><vector name="navel" x="0" y="0"/></imgdir><string name="z" value="shoes"/><string name="_hash" value="0e2ebba18faabfa3d28ea9c48d938f318a8ea59a6ed64e4cdbf548d80abb0880"/></canvas></imgdir></imgdir><imgdir name="stabT1"><imgdir name="0"><canvas name="shoes" width="27" height="12"><vector name="origin" x="16" y="-8"/><imgdir name="map"><vector name="navel" x="0" y="0"/></imgdir><string name="z" value="shoes"/><string name="_hash" value="c15686e9e7ac2b9b67791a9ccc024e953a6dbdc41ee834b5d9a59b846a05c0eb"/></canvas></imgdir><imgdir name="1"><canvas name="shoes" width="31" height="12"><vector name="origin" x="7" y="-7"/><imgdir name="map"><vector name="navel" x="0" y="0"/></imgdir><string name="z" value="shoes"/><string name="_hash" value="2d1863cd43906910781b30bba2eaba9b56a8e83e16416c4425d406ad575dce24"/></canvas></imgdir><imgdir name="2"><canvas name="shoes" width="41" height="13"><vector name="origin" x="13" y="-2"/><imgdir name="map"><vector name="navel" x="0" y="0"/></imgdir><string name="z" value="shoes"/><string name="_hash" value="0febd095c64e0fbf4587f568b87b2dc63d25b0d8599de2779512deee8c279475"/></canvas></imgdir></imgdir><imgdir name="stabT2"><imgdir name="0"><canvas name="shoes" width="23" height="13"><vector name="origin" x="10" y="-6"/><imgdir name="map"><vector name="navel" x="0" y="0"/></imgdir><string name="z" value="shoes"/><string name="_hash" value="7055958dbe8b924ea52907471a1813477d4fbe283949a76ac82ba549dcc61f81"/></canvas></imgdir><imgdir name="1"><canvas name="shoes" width="30" height="12"><vector name="origin" x="10" y="-5"/><imgdir name="map"><vector name="navel" x="0" y="0"/></imgdir><string name="z" value="shoes"/><string name="_hash" value="dbadda78f0dfe12651e284e2924e4789f8e0fed9bfced8b5893e68c04a89e049"/></canvas></imgdir><imgdir name="2"><canvas name="shoes" width="44" height="13"><vector name="origin" x="15" y="-2"/><imgdir name="map"><vector name="navel" x="0" y="0"/></imgdir><string name="z" value="shoes"/><string name="_hash" value="85dab78716f21682b73c50a1a1846ffb971eb202948c58f0cadd8b80bc105a8a"/></canvas></imgdir></imgdir><imgdir name="proneStab"><imgdir name="0"><canvas name="shoes" width="16" height="7"><vector name="origin" x="-7" y="4"/><imgdir name="map"><vector name="navel" x="0" y="0"/></imgdir><string name="z" value="shoes"/><string name="_hash" value="7a6ad899f8248b3fcfe862781b7c9c2b776f371c23646768129a50fce8e058e1"/></canvas></imgdir><imgdir name="1"><uol name="shoes" value="../0/shoes"/></imgdir></imgdir><imgdir name="stabTF"><imgdir name="0"><uol name="shoes" value="../../swingPF/0/shoes"/></imgdir><imgdir name="1"><uol name="shoes" value="../../swingPF/1/shoes"/></imgdir><imgdir name="2"><canvas name="shoes" width="22" height="24"><vector name="origin" x="12" y="-6"/><imgdir name="map"><vector name="navel" x="0" y="0"/></imgdir><string name="z" value="shoes"/><string name="_hash" value="f462ba39ed7e5236cee13aa5ef9eae4c101b139c435b81c69e7641931a96b5f5"/><string name="_outlink" value="Character/Shoes/01072921.img/stabTF/2/shoes"/></canvas></imgdir><imgdir name="3"><uol name="shoes" value="../../stabT1/2/shoes"/></imgdir></imgdir><imgdir name="fly"><imgdir name="0"><canvas name="shoes" width="18" height="19"><vector name="origin" x="1" y="-5"/><imgdir name="map"><vector name="navel" x="0" y="0"/></imgdir><string name="z" value="shoes"/><string name="_hash" value="72db88d31209240f4f1e1759f209f801369d3a0b946c6ee83df5b52539ae0f08"/></canvas></imgdir><imgdir name="1"><canvas name="shoes" width="13" height="16"><vector name="origin" x="0" y="-8"/><imgdir name="map"><vector name="navel" x="0" y="0"/></imgdir><string name="z" value="shoes"/><string name="_hash" value="c62e18804957f09836be3489c81521e6963a3d63df2415667184a5dfa3d18e19"/></canvas></imgdir></imgdir><imgdir name="jump"><imgdir name="0"><canvas name="shoes" width="36" height="13"><vector name="origin" x="17" y="-5"/><imgdir name="map"><vector name="navel" x="0" y="0"/></imgdir><string name="z" value="shoes"/><string name="_hash" value="70d97d740acc92c4fa9ff4e12a35ac36d896cfd51e4d58f59b361f2a7a4c38ac"/></canvas></imgdir></imgdir><imgdir name="shoot1"><imgdir name="0"><canvas name="shoes" width="24" height="12"><vector name="origin" x="13" y="-8"/><imgdir name="map"><vector name="navel" x="0" y="0"/></imgdir><string name="z" value="shoes"/><string name="_hash" value="e5347f20448512254e0dcdc16cbc275cab174538a8cd0af680ad43cadf37d4a1"/></canvas></imgdir><imgdir name="1"><canvas name="shoes" width="24" height="12"><vector name="origin" x="13" y="-8"/><imgdir name="map"><vector name="navel" x="0" y="0"/></imgdir><string name="z" value="shoes"/><string name="_inlink" value="shoot1/0/shoes"/></canvas></imgdir><imgdir name="2"><uol name="shoes" value="../1/shoes"/></imgdir></imgdir><imgdir name="shoot2"><imgdir name="0"><canvas name="shoes" width="24" height="12"><vector name="origin" x="11" y="-7"/><imgdir name="map"><vector name="navel" x="0" y="0"/></imgdir><string name="z" value="shoes"/><string name="_hash" value="95c42cf766f3858e3bea85ae7a951ba113c2b739abbd1b8f926dcddb90106eb5"/></canvas></imgdir><imgdir name="1"><uol name="shoes" value="../0/shoes"/></imgdir><imgdir name="2"><uol name="shoes" value="../0/shoes"/></imgdir><imgdir name="3"><uol name="shoes" value="../0/shoes"/></imgdir><imgdir name="4"><uol name="shoes" value="../0/shoes"/></imgdir></imgdir><imgdir name="shootF"><imgdir name="0"><canvas name="shoes" width="25" height="12"><vector name="origin" x="16" y="-8"/><imgdir name="map"><vector name="navel" x="0" y="0"/></imgdir><string name="z" value="shoes"/><string name="_hash" value="7def9f9e14aacfcf5e2c9766eaec16704abba75673a2623b03a16f8fe7da6a24"/></canvas></imgdir><imgdir name="1"><canvas name="shoes" width="28" height="12"><vector name="origin" x="16" y="-7"/><imgdir name="map"><vector name="navel" x="0" y="0"/></imgdir><string name="z" value="shoes"/><string name="_hash" value="a48caaf008049887af19a03328cdb4ef2c4d22fcd37a50b344745fae9848f7f9"/></canvas></imgdir><imgdir name="2"><uol name="shoes" value="../1/shoes"/></imgdir></imgdir><imgdir name="swingP1"><imgdir name="0"><canvas name="shoes" width="23" height="13"><vector name="origin" x="12" y="-8"/><imgdir name="map"><vector name="navel" x="0" y="0"/></imgdir><string name="z" value="shoes"/><string name="_inlink" value="swingT1/0/shoes"/></canvas></imgdir><imgdir name="1"><canvas name="shoes" width="28" height="12"><vector name="origin" x="12" y="-6"/><imgdir name="map"><vector name="navel" x="0" y="0"/></imgdir><string name="z" value="shoes"/><string name="_inlink" value="swingT1/1/shoes"/></canvas></imgdir><imgdir name="2"><canvas name="shoes" width="37" height="13"><vector name="origin" x="10" y="-4"/><imgdir name="map"><vector name="navel" x="0" y="0"/></imgdir><string name="z" value="shoes"/><string name="_inlink" value="swingT2/2/shoes"/></canvas></imgdir></imgdir><imgdir name="swingP2"><imgdir name="0"><canvas name="shoes" width="25" height="13"><vector name="origin" x="11" y="-8"/><imgdir name="map"><vector name="navel" x="0" y="0"/></imgdir><string name="z" value="shoes"/><string name="_hash" value="c491703202414398ff5ac3952be3b34896fa141b4a0b30ba40a4d4df3067385d"/></canvas></imgdir><imgdir name="1"><canvas name="shoes" width="28" height="12"><vector name="origin" x="12" y="-7"/><imgdir name="map"><vector name="navel" x="0" y="0"/></imgdir><string name="z" value="shoes"/><string name="_inlink" value="swingO2/1/shoes"/></canvas></imgdir><imgdir name="2"><canvas name="shoes" width="37" height="13"><vector name="origin" x="11" y="-4"/><imgdir name="map"><vector name="navel" x="0" y="0"/></imgdir><string name="z" value="shoes"/><string name="_inlink" value="swingT2/2/shoes"/></canvas></imgdir></imgdir><imgdir name="swingPF"><imgdir name="0"><canvas name="shoes" width="39" height="11"><vector name="origin" x="12" y="-5"/><imgdir name="map"><vector name="navel" x="0" y="0"/></imgdir><string name="z" value="shoes"/><string name="_hash" value="cce5390feb7e540fa984179542e3a6f40ee1bb70da72c1bc5899c278ce50c7bb"/></canvas></imgdir><imgdir name="1"><canvas name="shoes" width="37" height="11"><vector name="origin" x="11" y="-4"/><imgdir name="map"><vector name="navel" x="0" y="0"/></imgdir><string name="z" value="shoes"/><string name="_hash" value="8ad9b5843a86449ca248cb2e61dec9303e61870c2bd7ddfc8666769c5a3b4702"/></canvas></imgdir><imgdir name="2"><canvas name="shoes" width="22" height="24"><vector name="origin" x="12" y="-6"/><imgdir name="map"><vector name="navel" x="0" y="0"/></imgdir><string name="z" value="shoes"/><string name="_outlink" value="Character/Shoes/01072921.img/stabTF/2/shoes"/></canvas></imgdir><imgdir name="3"><canvas name="shoes" width="19" height="11"><vector name="origin" x="10" y="-6"/><imgdir name="map"><vector name="navel" x="0" y="0"/></imgdir><string name="z" value="shoes"/><string name="_hash" value="262fb47fcb0abe92b95451741572ff6ca4ac68be1dab20ed46aad9587ea0077f"/></canvas></imgdir></imgdir><imgdir name="stabOF"><imgdir name="0"><canvas name="shoes" width="19" height="12"><vector name="origin" x="11" y="-3"/><imgdir name="map"><vector name="navel" x="0" y="0"/></imgdir><string name="z" value="shoes"/><string name="_hash" value="86b175c9144fa75eadb8e33183015120614135b19a3af48b4cbdc90167256a01"/></canvas></imgdir><imgdir name="1"><canvas name="shoes" width="38" height="13"><vector name="origin" x="20" y="-6"/><imgdir name="map"><vector name="navel" x="0" y="0"/></imgdir><string name="z" value="shoes"/><string name="_hash" value="f58e9a55177948f8adbb66d833872dbf63e5e7516d256696999f323a820d8751"/></canvas></imgdir><imgdir name="2"><canvas name="shoes" width="37" height="12"><vector name="origin" x="12" y="-4"/><imgdir name="map"><vector name="navel" x="0" y="0"/></imgdir><string name="z" value="shoes"/><string name="_hash" value="2f941f0a38cac6a931b527b97091fabbca5077e30268f444e2aca0de5d029de4"/></canvas></imgdir></imgdir><imgdir name="rope"><imgdir name="0"><canvas name="shoes" width="15" height="15"><vector name="origin" x="8" y="-9"/><imgdir name="map"><vector name="navel" x="0" y="0"/></imgdir><string name="z" value="backShoes"/><string name="_hash" value="d527c9b0e02cbf892f70df560e04369e4c44525672b210efc35f1ec79a910aea"/></canvas></imgdir><imgdir name="1"><canvas name="shoes" width="19" height="11"><vector name="origin" x="9" y="-7"/><imgdir name="map"><vector name="navel" x="0" y="0"/></imgdir><string name="z" value="backShoes"/><string name="_hash" value="2d2478c9ae72933311529e4054e23701f6260e55b3d3f50befbc8941e811401e"/></canvas></imgdir></imgdir><imgdir name="prone"><imgdir name="0"><uol name="shoes" value="../../proneStab/0/shoes"/></imgdir></imgdir><imgdir name="heal"><imgdir name="0"><uol name="shoes" value="../../alert/1/shoes"/></imgdir><imgdir name="1"><uol name="shoes" value="../../swingO2/1/shoes"/></imgdir><imgdir name="2"><uol name="shoes" value="../../swingO2/0/shoes"/></imgdir></imgdir><imgdir name="sit"><imgdir name="0"><canvas name="shoes" width="21" height="11"><vector name="origin" x="17" y="-4"/><imgdir name="map"><vector name="navel" x="0" y="0"/></imgdir><string name="z" value="shoes"/><string name="_hash" value="2ecd747d911a84e3ab70213e04786367d6a375d7f97b7748a6a73b054a0dcb24"/></canvas></imgdir></imgdir></imgdir>